[
  {
    "question": "おなかに　できる　ホタチは　たたかうとき　だけでなく　かたい　きのみを　わるときにも　つかう。　",
    "answer": "ミジュマル",
    "game": "ポケットモンスター Ｘ"
  },
  {
    "question": "キメ細やかな　毛皮の　持ち主。　怒らせると　どんどん　ふくらみ　のしかかってくるので　注意。　",
    "answer": "プクリン",
    "game": "ポケットモンスター スカーレット"
  },
  {
    "question": "動きが　のろく　間抜け。　叩かれても　５秒　たってから　痛さを　感じるほどだ。　",
    "answer": "ヤドン",
    "game": "ポケットモンスター スカーレット"
  },
  {
    "question": "はなびらの　おおきさは　せかいいち。　ひどい　アレルギーを　ひきおこす　どくかふんを　ばらまいて　あるく。　",
    "answer": "ラフレシア",
    "game": "ポケットモンスター ブリリアントダイヤモンド・シャイニングパール"
  },
  {
    "question": "命を　奪おうと　決めた　獲物の　影に　潜り込み　じっと　チャンスを　狙ってる。",
    "answer": "ゲンガー",
    "game": "ポケットモンスター スカーレット"
  },
  {
    "question": "どこまでも　えものを　おいつづける　しゅうねんぶかい　せいかくだが　あさひが　のぼると　あきらめる。",
    "answer": "ヨワマル",
    "game": "ポケットモンスター ブリリアントダイヤモンド・シャイニングパール"
  },
  {
    "question": "よなよな　いせきを　さまよう。　もっている　マスクは　ひと　だった　ころの　じぶんの　かお　だという。　",
    "answer": "デスマス",
    "game": "ポケットモンスター ソード"
  },
  {
    "question": "幼子　惑わし　彼岸へ　連れ去ると　伝えられし　ポケモン。　人魂より　転生したと　噂あるも　真偽不明なり。",
    "answer": "フワンテ",
    "game": "Pokémon LEGENDS アルセウス"
  },
  {
    "question": "だれかが　しぬ　ちょくぜんに　あらわれる　ことから　しにがみの　つかい　として　おそれられている。",
    "answer": "ランプラー",
    "game": "ポケットモンスター ソード"
  },
  {
    "question": "すいとる　いのちが　わかければ　わかいほど　あたまの　ほのおは　おおきく　あやしく　もえあがる。",
    "answer": "ヒトモシ",
    "game": "ポケットモンスター シールド"
  },
  {
    "question": "リボン状の器官より　怒りを　鎮める　気を　放つ。　諍う者　あれば　これを　巻きつけ　たちまち　場を　和ます。　",
    "answer": "ニンフィア",
    "game": "Pokémon LEGENDS アルセウス"
  },
  {
    "question": "心臓や　脳みそは　小さく　体の　大部分が　胃袋。　なんでも　溶かす　胃液を　出す。　",
    "answer": "ゴクリン",
    "game": "ポケットモンスター バイオレット"
  },
  {
    "question": "壁をすり抜け　何処にでも　姿　現す　恐ろしき悪霊。　舌で　舐められし者　日に日に　衰弱し　死に至るとの噂。　",
    "answer": "ゴースト",
    "game": "Pokémon LEGENDS アルセウス"
  },
  {
    "question": "ピカピカの　おうごんの　からだ。　もはや　にんげんだった　ことは　おもいだすことは　ないと　いう。",
    "answer": "デスカーン",
    "game": "ポケットモンスター ソード"
  },
  {
    "question": "かぼちゃの　あなから　てらしている　ひかりは　みた　ひとや　ポケモンを　さいみんじょうたいにして　あやつる。　",
    "answer": "バケッチャ",
    "game": "ポケットモンスター シールド"
  },
  {
    "question": "ポケモンだと　認識されたのは　最近のこと。　それまでは　布を　被った　おばけと　思われていた。　",
    "answer": "ミミッキュ",
    "game": "ポケットモンスター バイオレット"
  },
  {
    "question": "地面　深くで　生まれ　山ほどの　土を　食べ終わると　体を　つくるため　サナギになる。",
    "answer": "ヨーギラス",
    "game": "ポケットモンスター スカーレット"
  },
  {
    "question": "頬に　電気を溜めし　袋を　有す。　森林を　棲み処とし　硬き　木の実は　電撃で　焼き　食べる　知恵者なり。　",
    "answer": "ピカチュウ",
    "game": "Pokémon LEGENDS アルセウス"
  },
  {
    "question": "皮膚が　とても　薄いので　光に　照らされると　血液が　温められて　弱ってしまう。　",
    "answer": "ディグダ",
    "game": "ポケットモンスター バイオレット"
  },
  {
    "question": "スーパーコンピュータなみの　ずのう。　はったつした　ずのうは　あらゆる　ちょうのうりょくを　つかいこなす。",
    "answer": "フーディン",
    "game": "ポケットモンスター シャイニングパール"
  },
  {
    "question": "クキが　なくなると　いきていけない。　だから　クキを　ねらう　あいてとは　いのちがけで　たたかうのだ。　",
    "answer": "カモネギ",
    "game": "ポケットモンスター ブリリアントダイヤモンド・シャイニングパール"
  },
  {
    "question": "振る舞い　パントマイムが如く。　道化師　思い起こす　姿にて　指先より　発す　気力　用いて　透明な壁を作る。　",
    "answer": "バリヤード",
    "game": "Pokémon LEGENDS アルセウス"
  },
  {
    "question": "不規則な　遺伝子を　持つ。　石から出る　放射線によって　体が　突然変異を　起こす。",
    "answer": "イーブイ",
    "game": "ポケットモンスター バイオレット"
  },
  {
    "question": "生まれたときから　すでに　大きい。　脱皮を　繰り返しては　どんどん　育って　長くなる。　",
    "answer": "ミニリュウ",
    "game": "ポケットモンスター バイオレット"
  },
  {
    "question": "カラの　なかに　たくさん　しあわせが　つまっていて　やさしい　ひとに　しあわせを　わけあたえるという。　",
    "answer": "トゲピー",
    "game": "ポケットモンスター ブリリアントダイヤモンド・シャイニングパール"
  },
  {
    "question": "尻尾の　灯りは　遠くまで　届くので　昔より　かがり火として　大事に　されている。　",
    "answer": "デンリュウ",
    "game": "ポケットモンスター スカーレット"
  },
  {
    "question": "くろい　しっぽを　ひっしになって　かくすのは　しっぽに　ひみつがある　しょうこだと　かんぐられている。",
    "answer": "ソーナンス",
    "game": "ポケットモンスター ブリリアントダイヤモンド・シャイニングパール"
  },
  {
    "question": "テレパシーを　つかい　なかまどうしで　いしそつうを　しているらしい。　いつも　かべに　はりついている。",
    "answer": "アンノーン",
    "game": "ポケットモンスター シャイニングパール"
  },
  {
    "question": "心音　聞こえず　呼吸の気配すら　窺えぬが　活動に　支障なき様子。　奇天烈すぎるゆえ　皆目　見当つかず。　",
    "answer": "ポリゴン",
    "game": "Pokémon LEGENDS アルセウス"
  },
  {
    "question": "",
    "answer": "",
    "game": ""
  },
  {
    "question": "",
    "answer": "",
    "game": ""
  },
  {
    "question": "",
    "answer": "",
    "game": ""
  },
  {
    "question": "",
    "answer": "",
    "game": ""
  }
]